<?xml version="1.0" encoding="UTF-8"?>
<CTRLWIDGET>
	<Group>
		<Item id="1" name="mLetB" type="BUTTON" visible="true"></Item>
		<Item id="3" name="mLetC" type="BUTTON" visible="true"></Item>
		<Item id="6" name="ABC" type="BUTTON" visible="true"></Item>
		<Item id="7" name="mLetF" type="BUTTON" visible="true"></Item>
		<Item id="8" name="mLetI" type="BUTTON" visible="true"></Item>
		<Item id="9" name="mLetA" type="BUTTON" visible="true"></Item>
		<Item id="10" name="mLetH" type="BUTTON" visible="true"></Item>
		<Item id="11" name="mLetE" type="BUTTON" visible="true"></Item>
		<Item id="12" name="mLetG" type="BUTTON" visible="true"></Item>
		<Item id="13" name="mLetD" type="BUTTON" visible="true"></Item>
		<Item id="15" name="icon_keyboard_full" type="BUTTON" visible="true"></Item>
		<Item id="16" name="mSignSpace" type="BUTTON" visible="true"></Item>
		<Item id="17" name="mFuncEnter" type="BUTTON" visible="true"></Item>
		<Item id="18" name="mSignNumbers" type="BUTTON" visible="true"></Item>
		<Item id="19" name="mSignSymbol" type="BUTTON" visible="true"></Item>
		<Item id="20" name="ANO" type="BUTTON" visible="true"></Item>
		<Item id="22" name="JKL" type="BUTTON" visible="true"></Item>
		<Item id="23" name="STU" type="BUTTON" visible="true"></Item>
	</Group>
</CTRLWIDGET>
