<?xml version="1.0" encoding="UTF-8"?>
<SCREEN>
	<Group>
		<Item id="1" name="Header" type="REFFUNCWIDGET" visible="true"></Item>
		<Item id="2" name="Home" type="REFFUNCWIDGET" visible="true"></Item>
		<Item id="3" name="TEXT" type="BUTTON" visible="true"></Item>
		<Item id="4" name="LIST" type="LIST" visible="true"></Item>
		<Item id="5" name="txtbase" type="IMAGEFIELD" visible="true"></Item>
		<Item id="6" name="Dealer_info_one" type="TEXTFIELD" visible="true"></Item>
		<Item id="8" name="by_Map_pointing" type="BUTTON" visible="true"></Item>
		<Item id="9" name="Set" type="BUTTON" visible="true"></Item>
		<Item id="10" name="Dealer_info_two" type="TEXTFIELD" visible="true"></Item>
		<Item id="12" name="Dealer_info_four" type="TEXTFIELD" visible="true"></Item>
	</Group>
</SCREEN>
