<?xml version="1.0" encoding="UTF-8"?>
<CTRLWIDGET>
	<Group>
		<Item id="1" name="mNum2" type="BUTTON"></Item>
		<Item id="2" name="mNum3" type="BUTTON"></Item>
		<Item id="3" name="mNum6" type="BUTTON"></Item>
		<Item id="4" name="mNum9" type="BUTTON"></Item>
		<Item id="5" name="mNum1" type="BUTTON"></Item>
		<Item id="6" name="mNum8" type="BUTTON"></Item>
		<Item id="7" name="mNum5" type="BUTTON"></Item>
		<Item id="8" name="mNum7" type="BUTTON"></Item>
		<Item id="9" name="mNum4" type="BUTTON"></Item>
		<Item id="10" name="mFuncKeyboard" type="BUTTON"></Item>
		<Item id="11" name="mSignSpace" type="BUTTON"></Item>
		<Item id="12" name="mFuncEnter" type="BUTTON"></Item>
		<Item id="13" name="mFuncABC" type="BUTTON"></Item>
		<Item id="14" name="mFuncSpclChars" type="BUTTON"></Item>
		<Item id="15" name="mFuncLatANO" type="BUTTON"></Item>
		<Item id="16" name="mFuncDelete" type="BUTTON"></Item>
		<Item id="17" name="mNum0" type="BUTTON"></Item>
	</Group>
</CTRLWIDGET>
