<?xml version="1.0" encoding="UTF-8"?>
<SCREEN>
	<Group>
		<Item id="1" name="Header" type="REFFUNCWIDGET" visible="true"></Item>
		<Item id="2" name="Home" type="REFFUNCWIDGET" visible="true"></Item>
		<Item id="3" name="Phone_number" type="TEXTFIELD" visible="true"></Item>
		<Item id="4" name="Dialling_message" type="TEXTFIELD" visible="true"></Item>
		<Item TOUCH_PRESSED="true" id="5" name="Cancel" type="BUTTON" visible="true"></Item>
		<Item id="6" name="icon_phone" type="IMAGEFIELD"></Item>
	</Group>
</SCREEN>
